[
  {
    "componentName": "Button",
    "filePath": "C:\\xampp\\htdocs\\projects\\python\\caspian-web\\src\\lib\\caspian_ui\\Button.py",
    "relativePath": "src/lib/caspian_ui/Button.py",
    "importRoute": "src.lib.caspian_ui.Button",
    "acceptsArbitraryProps": true,
    "props": [
      {
        "name": "children",
        "type": "Any",
        "hasDefault": true,
        "defaultValue": ""
      },
      {
        "name": "variant",
        "type": "button_variant",
        "hasDefault": true,
        "defaultValue": "default",
        "options": [
          "default",
          "destructive",
          "outline",
          "secondary",
          "ghost",
          "link"
        ]
      },
      {
        "name": "size",
        "type": "button_size",
        "hasDefault": true,
        "defaultValue": "default",
        "options": [
          "default",
          "sm",
          "lg",
          "icon",
          "icon-sm",
          "icon-lg"
        ]
      },
      {
        "name": "asChild",
        "type": "Literal[True, False]",
        "hasDefault": true,
        "defaultValue": "False"
      }
    ]
  },
  {
    "componentName": "Command",
    "filePath": "C:\\xampp\\htdocs\\projects\\python\\caspian-web\\src\\lib\\caspian_ui\\Command.py",
    "relativePath": "src/lib/caspian_ui/Command.py",
    "importRoute": "src.lib.caspian_ui.Command",
    "acceptsArbitraryProps": false,
    "props": [
      {
        "name": "class_name",
        "type": "str",
        "hasDefault": true,
        "defaultValue": ""
      },
      {
        "name": "id",
        "type": "str",
        "hasDefault": true,
        "defaultValue": ""
      },
      {
        "name": "children",
        "type": "str",
        "hasDefault": true,
        "defaultValue": ""
      }
    ]
  },
  {
    "componentName": "CommandDialog",
    "filePath": "C:\\xampp\\htdocs\\projects\\python\\caspian-web\\src\\lib\\caspian_ui\\Command.py",
    "relativePath": "src/lib/caspian_ui/Command.py",
    "importRoute": "src.lib.caspian_ui.Command",
    "acceptsArbitraryProps": false,
    "props": [
      {
        "name": "children",
        "type": "str",
        "hasDefault": true,
        "defaultValue": ""
      },
      {
        "name": "class_name",
        "type": "str",
        "hasDefault": true,
        "defaultValue": ""
      },
      {
        "name": "title",
        "type": "str",
        "hasDefault": true,
        "defaultValue": ""
      },
      {
        "name": "description",
        "type": "str",
        "hasDefault": true,
        "defaultValue": ""
      },
      {
        "name": "open",
        "type": "str",
        "hasDefault": true,
        "defaultValue": ""
      },
      {
        "name": "onOpenChange",
        "type": "str",
        "hasDefault": true,
        "defaultValue": ""
      }
    ]
  },
  {
    "componentName": "CommandInput",
    "filePath": "C:\\xampp\\htdocs\\projects\\python\\caspian-web\\src\\lib\\caspian_ui\\Command.py",
    "relativePath": "src/lib/caspian_ui/Command.py",
    "importRoute": "src.lib.caspian_ui.Command",
    "acceptsArbitraryProps": true,
    "props": [
      {
        "name": "class_name",
        "type": "str",
        "hasDefault": true,
        "defaultValue": ""
      },
      {
        "name": "placeholder",
        "type": "str",
        "hasDefault": true,
        "defaultValue": "Type a command or search..."
      }
    ]
  },
  {
    "componentName": "CommandList",
    "filePath": "C:\\xampp\\htdocs\\projects\\python\\caspian-web\\src\\lib\\caspian_ui\\Command.py",
    "relativePath": "src/lib/caspian_ui/Command.py",
    "importRoute": "src.lib.caspian_ui.Command",
    "acceptsArbitraryProps": false,
    "props": [
      {
        "name": "class_name",
        "type": "str",
        "hasDefault": true,
        "defaultValue": ""
      },
      {
        "name": "children",
        "type": "str",
        "hasDefault": true,
        "defaultValue": ""
      }
    ]
  },
  {
    "componentName": "CommandEmpty",
    "filePath": "C:\\xampp\\htdocs\\projects\\python\\caspian-web\\src\\lib\\caspian_ui\\Command.py",
    "relativePath": "src/lib/caspian_ui/Command.py",
    "importRoute": "src.lib.caspian_ui.Command",
    "acceptsArbitraryProps": false,
    "props": [
      {
        "name": "class_name",
        "type": "str",
        "hasDefault": true,
        "defaultValue": ""
      },
      {
        "name": "children",
        "type": "str",
        "hasDefault": true,
        "defaultValue": "No results found."
      }
    ]
  },
  {
    "componentName": "CommandGroup",
    "filePath": "C:\\xampp\\htdocs\\projects\\python\\caspian-web\\src\\lib\\caspian_ui\\Command.py",
    "relativePath": "src/lib/caspian_ui/Command.py",
    "importRoute": "src.lib.caspian_ui.Command",
    "acceptsArbitraryProps": false,
    "props": [
      {
        "name": "class_name",
        "type": "str",
        "hasDefault": true,
        "defaultValue": ""
      },
      {
        "name": "children",
        "type": "str",
        "hasDefault": true,
        "defaultValue": ""
      },
      {
        "name": "heading",
        "type": "str",
        "hasDefault": true,
        "defaultValue": ""
      }
    ]
  },
  {
    "componentName": "CommandSeparator",
    "filePath": "C:\\xampp\\htdocs\\projects\\python\\caspian-web\\src\\lib\\caspian_ui\\Command.py",
    "relativePath": "src/lib/caspian_ui/Command.py",
    "importRoute": "src.lib.caspian_ui.Command",
    "acceptsArbitraryProps": false,
    "props": [
      {
        "name": "class_name",
        "type": "str",
        "hasDefault": true,
        "defaultValue": ""
      }
    ]
  },
  {
    "componentName": "CommandItem",
    "filePath": "C:\\xampp\\htdocs\\projects\\python\\caspian-web\\src\\lib\\caspian_ui\\Command.py",
    "relativePath": "src/lib/caspian_ui/Command.py",
    "importRoute": "src.lib.caspian_ui.Command",
    "acceptsArbitraryProps": true,
    "props": [
      {
        "name": "children",
        "type": "str",
        "hasDefault": true,
        "defaultValue": ""
      },
      {
        "name": "onselect",
        "type": "str",
        "hasDefault": true,
        "defaultValue": ""
      }
    ]
  },
  {
    "componentName": "CommandShortcut",
    "filePath": "C:\\xampp\\htdocs\\projects\\python\\caspian-web\\src\\lib\\caspian_ui\\Command.py",
    "relativePath": "src/lib/caspian_ui/Command.py",
    "importRoute": "src.lib.caspian_ui.Command",
    "acceptsArbitraryProps": false,
    "props": [
      {
        "name": "children",
        "type": "str",
        "hasDefault": true,
        "defaultValue": ""
      },
      {
        "name": "class_name",
        "type": "str",
        "hasDefault": true,
        "defaultValue": ""
      }
    ]
  },
  {
    "componentName": "Dialog",
    "filePath": "C:\\xampp\\htdocs\\projects\\python\\caspian-web\\src\\lib\\caspian_ui\\Dialog.py",
    "relativePath": "src/lib/caspian_ui/Dialog.py",
    "importRoute": "src.lib.caspian_ui.Dialog",
    "acceptsArbitraryProps": true,
    "props": [
      {
        "name": "children",
        "type": "Any",
        "hasDefault": true,
        "defaultValue": ""
      },
      {
        "name": "open",
        "type": "Optional[str]",
        "hasDefault": true,
        "defaultValue": "None"
      },
      {
        "name": "onOpenChange",
        "type": "Optional[str]",
        "hasDefault": true,
        "defaultValue": "None"
      },
      {
        "name": "closeOnOverlayClick",
        "type": "bool",
        "hasDefault": true,
        "defaultValue": "True"
      },
      {
        "name": "resetOnOpen",
        "type": "bool",
        "hasDefault": true,
        "defaultValue": "False"
      },
      {
        "name": "overlayClass",
        "type": "Optional[str]",
        "hasDefault": true,
        "defaultValue": "None"
      },
      {
        "name": "className",
        "type": "Optional[str]",
        "hasDefault": true,
        "defaultValue": "None"
      },
      {
        "name": "id",
        "type": "Optional[str]",
        "hasDefault": true,
        "defaultValue": "None"
      }
    ]
  },
  {
    "componentName": "DialogTrigger",
    "filePath": "C:\\xampp\\htdocs\\projects\\python\\caspian-web\\src\\lib\\caspian_ui\\Dialog.py",
    "relativePath": "src/lib/caspian_ui/Dialog.py",
    "importRoute": "src.lib.caspian_ui.Dialog",
    "acceptsArbitraryProps": true,
    "props": [
      {
        "name": "children",
        "type": "Any",
        "hasDefault": true,
        "defaultValue": ""
      },
      {
        "name": "asChild",
        "type": "bool",
        "hasDefault": true,
        "defaultValue": "False"
      },
      {
        "name": "class_name",
        "type": "Optional[str]",
        "hasDefault": true,
        "defaultValue": "None"
      }
    ]
  },
  {
    "componentName": "DialogClose",
    "filePath": "C:\\xampp\\htdocs\\projects\\python\\caspian-web\\src\\lib\\caspian_ui\\Dialog.py",
    "relativePath": "src/lib/caspian_ui/Dialog.py",
    "importRoute": "src.lib.caspian_ui.Dialog",
    "acceptsArbitraryProps": true,
    "props": [
      {
        "name": "children",
        "type": "Any",
        "hasDefault": true,
        "defaultValue": ""
      },
      {
        "name": "asChild",
        "type": "bool",
        "hasDefault": true,
        "defaultValue": "False"
      },
      {
        "name": "class_name",
        "type": "str",
        "hasDefault": true,
        "defaultValue": ""
      }
    ]
  },
  {
    "componentName": "DialogOverlay",
    "filePath": "C:\\xampp\\htdocs\\projects\\python\\caspian-web\\src\\lib\\caspian_ui\\Dialog.py",
    "relativePath": "src/lib/caspian_ui/Dialog.py",
    "importRoute": "src.lib.caspian_ui.Dialog",
    "acceptsArbitraryProps": true,
    "props": [
      {
        "name": "children",
        "type": "Any",
        "hasDefault": true,
        "defaultValue": ""
      },
      {
        "name": "class_name",
        "type": "str",
        "hasDefault": true,
        "defaultValue": ""
      },
      {
        "name": "overlay_state_class",
        "type": "str",
        "hasDefault": true,
        "defaultValue": ""
      }
    ]
  },
  {
    "componentName": "DialogContent",
    "filePath": "C:\\xampp\\htdocs\\projects\\python\\caspian-web\\src\\lib\\caspian_ui\\Dialog.py",
    "relativePath": "src/lib/caspian_ui/Dialog.py",
    "importRoute": "src.lib.caspian_ui.Dialog",
    "acceptsArbitraryProps": true,
    "props": [
      {
        "name": "children",
        "type": "Any",
        "hasDefault": true,
        "defaultValue": ""
      },
      {
        "name": "class_name",
        "type": "str",
        "hasDefault": true,
        "defaultValue": ""
      },
      {
        "name": "disable_portal",
        "type": "bool",
        "hasDefault": true,
        "defaultValue": "False"
      },
      {
        "name": "portal_to",
        "type": "str",
        "hasDefault": true,
        "defaultValue": "body"
      },
      {
        "name": "portal_id",
        "type": "Optional[str]",
        "hasDefault": true,
        "defaultValue": "None"
      },
      {
        "name": "overlay_class",
        "type": "str",
        "hasDefault": true,
        "defaultValue": ""
      }
    ]
  },
  {
    "componentName": "DialogHeader",
    "filePath": "C:\\xampp\\htdocs\\projects\\python\\caspian-web\\src\\lib\\caspian_ui\\Dialog.py",
    "relativePath": "src/lib/caspian_ui/Dialog.py",
    "importRoute": "src.lib.caspian_ui.Dialog",
    "acceptsArbitraryProps": true,
    "props": [
      {
        "name": "children",
        "type": "Any",
        "hasDefault": true,
        "defaultValue": ""
      },
      {
        "name": "class_name",
        "type": "str",
        "hasDefault": true,
        "defaultValue": ""
      }
    ]
  },
  {
    "componentName": "DialogFooter",
    "filePath": "C:\\xampp\\htdocs\\projects\\python\\caspian-web\\src\\lib\\caspian_ui\\Dialog.py",
    "relativePath": "src/lib/caspian_ui/Dialog.py",
    "importRoute": "src.lib.caspian_ui.Dialog",
    "acceptsArbitraryProps": true,
    "props": [
      {
        "name": "children",
        "type": "Any",
        "hasDefault": true,
        "defaultValue": ""
      },
      {
        "name": "class_name",
        "type": "str",
        "hasDefault": true,
        "defaultValue": ""
      }
    ]
  },
  {
    "componentName": "DialogTitle",
    "filePath": "C:\\xampp\\htdocs\\projects\\python\\caspian-web\\src\\lib\\caspian_ui\\Dialog.py",
    "relativePath": "src/lib/caspian_ui/Dialog.py",
    "importRoute": "src.lib.caspian_ui.Dialog",
    "acceptsArbitraryProps": true,
    "props": [
      {
        "name": "children",
        "type": "Any",
        "hasDefault": true,
        "defaultValue": ""
      },
      {
        "name": "class_name",
        "type": "str",
        "hasDefault": true,
        "defaultValue": ""
      }
    ]
  },
  {
    "componentName": "DialogDescription",
    "filePath": "C:\\xampp\\htdocs\\projects\\python\\caspian-web\\src\\lib\\caspian_ui\\Dialog.py",
    "relativePath": "src/lib/caspian_ui/Dialog.py",
    "importRoute": "src.lib.caspian_ui.Dialog",
    "acceptsArbitraryProps": true,
    "props": [
      {
        "name": "children",
        "type": "Any",
        "hasDefault": true,
        "defaultValue": ""
      },
      {
        "name": "class_name",
        "type": "str",
        "hasDefault": true,
        "defaultValue": ""
      }
    ]
  },
  {
    "componentName": "Input",
    "filePath": "C:\\xampp\\htdocs\\projects\\python\\caspian-web\\src\\lib\\caspian_ui\\Input.py",
    "relativePath": "src/lib/caspian_ui/Input.py",
    "importRoute": "src.lib.caspian_ui.Input",
    "acceptsArbitraryProps": true,
    "props": []
  },
  {
    "componentName": "Label",
    "filePath": "C:\\xampp\\htdocs\\projects\\python\\caspian-web\\src\\lib\\caspian_ui\\Label.py",
    "relativePath": "src/lib/caspian_ui/Label.py",
    "importRoute": "src.lib.caspian_ui.Label",
    "acceptsArbitraryProps": true,
    "props": [
      {
        "name": "children",
        "type": "Any",
        "hasDefault": true,
        "defaultValue": ""
      },
      {
        "name": "asChild",
        "type": "Any",
        "hasDefault": true,
        "defaultValue": "False"
      }
    ]
  },
  {
    "componentName": "Portal",
    "filePath": "C:\\xampp\\htdocs\\projects\\python\\caspian-web\\src\\lib\\caspian_ui\\Portal.py",
    "relativePath": "src/lib/caspian_ui/Portal.py",
    "importRoute": "src.lib.caspian_ui.Portal",
    "acceptsArbitraryProps": true,
    "props": [
      {
        "name": "children",
        "type": "Any",
        "hasDefault": true,
        "defaultValue": ""
      },
      {
        "name": "to",
        "type": "str",
        "hasDefault": true,
        "defaultValue": "body"
      }
    ]
  },
  {
    "componentName": "Sheet",
    "filePath": "C:\\xampp\\htdocs\\projects\\python\\caspian-web\\src\\lib\\caspian_ui\\Sheet.py",
    "relativePath": "src/lib/caspian_ui/Sheet.py",
    "importRoute": "src.lib.caspian_ui.Sheet",
    "acceptsArbitraryProps": true,
    "props": [
      {
        "name": "open",
        "type": "Optional[str]",
        "hasDefault": true,
        "defaultValue": "None"
      },
      {
        "name": "onOpenChange",
        "type": "Optional[str]",
        "hasDefault": true,
        "defaultValue": "None"
      },
      {
        "name": "closeOnOverlayClick",
        "type": "bool",
        "hasDefault": true,
        "defaultValue": "True"
      },
      {
        "name": "resetOnOpen",
        "type": "bool",
        "hasDefault": true,
        "defaultValue": "False"
      },
      {
        "name": "overlayClass",
        "type": "str",
        "hasDefault": true,
        "defaultValue": ""
      },
      {
        "name": "lockScroll",
        "type": "bool",
        "hasDefault": true,
        "defaultValue": "True"
      }
    ]
  },
  {
    "componentName": "SheetTrigger",
    "filePath": "C:\\xampp\\htdocs\\projects\\python\\caspian-web\\src\\lib\\caspian_ui\\Sheet.py",
    "relativePath": "src/lib/caspian_ui/Sheet.py",
    "importRoute": "src.lib.caspian_ui.Sheet",
    "acceptsArbitraryProps": true,
    "props": [
      {
        "name": "children",
        "type": "Any",
        "hasDefault": true,
        "defaultValue": ""
      },
      {
        "name": "asChild",
        "type": "bool",
        "hasDefault": true,
        "defaultValue": "False"
      },
      {
        "name": "class_name",
        "type": "Optional[str]",
        "hasDefault": true,
        "defaultValue": "None"
      }
    ]
  },
  {
    "componentName": "SheetClose",
    "filePath": "C:\\xampp\\htdocs\\projects\\python\\caspian-web\\src\\lib\\caspian_ui\\Sheet.py",
    "relativePath": "src/lib/caspian_ui/Sheet.py",
    "importRoute": "src.lib.caspian_ui.Sheet",
    "acceptsArbitraryProps": true,
    "props": [
      {
        "name": "children",
        "type": "Any",
        "hasDefault": true,
        "defaultValue": ""
      },
      {
        "name": "asChild",
        "type": "bool",
        "hasDefault": true,
        "defaultValue": "False"
      },
      {
        "name": "class_name",
        "type": "str",
        "hasDefault": true,
        "defaultValue": ""
      }
    ]
  },
  {
    "componentName": "SheetOverlay",
    "filePath": "C:\\xampp\\htdocs\\projects\\python\\caspian-web\\src\\lib\\caspian_ui\\Sheet.py",
    "relativePath": "src/lib/caspian_ui/Sheet.py",
    "importRoute": "src.lib.caspian_ui.Sheet",
    "acceptsArbitraryProps": true,
    "props": [
      {
        "name": "children",
        "type": "Any",
        "hasDefault": true,
        "defaultValue": ""
      },
      {
        "name": "class_name",
        "type": "str",
        "hasDefault": true,
        "defaultValue": ""
      },
      {
        "name": "overlay_state_class",
        "type": "str",
        "hasDefault": true,
        "defaultValue": ""
      }
    ]
  },
  {
    "componentName": "SheetContent",
    "filePath": "C:\\xampp\\htdocs\\projects\\python\\caspian-web\\src\\lib\\caspian_ui\\Sheet.py",
    "relativePath": "src/lib/caspian_ui/Sheet.py",
    "importRoute": "src.lib.caspian_ui.Sheet",
    "acceptsArbitraryProps": true,
    "props": [
      {
        "name": "children",
        "type": "Any",
        "hasDefault": true,
        "defaultValue": ""
      },
      {
        "name": "disablePortal",
        "type": "bool",
        "hasDefault": true,
        "defaultValue": "False"
      },
      {
        "name": "side",
        "type": "Literal[\"right\", \"left\", \"top\", \"bottom\"]",
        "hasDefault": true,
        "defaultValue": "right",
        "options": [
          "right",
          "left",
          "top",
          "bottom"
        ]
      }
    ]
  },
  {
    "componentName": "SheetHeader",
    "filePath": "C:\\xampp\\htdocs\\projects\\python\\caspian-web\\src\\lib\\caspian_ui\\Sheet.py",
    "relativePath": "src/lib/caspian_ui/Sheet.py",
    "importRoute": "src.lib.caspian_ui.Sheet",
    "acceptsArbitraryProps": true,
    "props": []
  },
  {
    "componentName": "SheetFooter",
    "filePath": "C:\\xampp\\htdocs\\projects\\python\\caspian-web\\src\\lib\\caspian_ui\\Sheet.py",
    "relativePath": "src/lib/caspian_ui/Sheet.py",
    "importRoute": "src.lib.caspian_ui.Sheet",
    "acceptsArbitraryProps": true,
    "props": []
  },
  {
    "componentName": "SheetTitle",
    "filePath": "C:\\xampp\\htdocs\\projects\\python\\caspian-web\\src\\lib\\caspian_ui\\Sheet.py",
    "relativePath": "src/lib/caspian_ui/Sheet.py",
    "importRoute": "src.lib.caspian_ui.Sheet",
    "acceptsArbitraryProps": true,
    "props": []
  },
  {
    "componentName": "SheetDescription",
    "filePath": "C:\\xampp\\htdocs\\projects\\python\\caspian-web\\src\\lib\\caspian_ui\\Sheet.py",
    "relativePath": "src/lib/caspian_ui/Sheet.py",
    "importRoute": "src.lib.caspian_ui.Sheet",
    "acceptsArbitraryProps": true,
    "props": []
  },
  {
    "componentName": "Slot",
    "filePath": "C:\\xampp\\htdocs\\projects\\python\\caspian-web\\src\\lib\\caspian_ui\\Slot.py",
    "relativePath": "src/lib/caspian_ui/Slot.py",
    "importRoute": "src.lib.caspian_ui.Slot",
    "acceptsArbitraryProps": true,
    "props": [
      {
        "name": "children",
        "type": "Any",
        "hasDefault": true,
        "defaultValue": ""
      },
      {
        "name": "asChild",
        "type": "Any",
        "hasDefault": true,
        "defaultValue": "False"
      }
    ]
  },
  {
    "componentName": "DocsSheet",
    "filePath": "C:\\xampp\\htdocs\\projects\\python\\caspian-web\\src\\lib\\components\\DocsSheet.py",
    "relativePath": "src/lib/components/DocsSheet.py",
    "importRoute": "src.lib.components.DocsSheet",
    "acceptsArbitraryProps": false,
    "props": [
      {
        "name": "open",
        "type": "str | None",
        "hasDefault": true,
        "defaultValue": "None"
      },
      {
        "name": "onOpenChange",
        "type": "str | None",
        "hasDefault": true,
        "defaultValue": "None"
      }
    ]
  },
  {
    "componentName": "HomeSheet",
    "filePath": "C:\\xampp\\htdocs\\projects\\python\\caspian-web\\src\\lib\\components\\HomeSheet.py",
    "relativePath": "src/lib/components/HomeSheet.py",
    "importRoute": "src.lib.components.HomeSheet",
    "acceptsArbitraryProps": false,
    "props": [
      {
        "name": "open",
        "type": "str | None",
        "hasDefault": true,
        "defaultValue": "None"
      },
      {
        "name": "onOpenChange",
        "type": "str | None",
        "hasDefault": true,
        "defaultValue": "None"
      }
    ]
  },
  {
    "componentName": "Activity",
    "filePath": "C:\\xampp\\htdocs\\projects\\python\\caspian-web\\src\\lib\\ppicons\\Activity.py",
    "relativePath": "src/lib/ppicons/Activity.py",
    "importRoute": "src.lib.ppicons.Activity",
    "acceptsArbitraryProps": true,
    "props": []
  },
  {
    "componentName": "AppWindow",
    "filePath": "C:\\xampp\\htdocs\\projects\\python\\caspian-web\\src\\lib\\ppicons\\AppWindow.py",
    "relativePath": "src/lib/ppicons/AppWindow.py",
    "importRoute": "src.lib.ppicons.AppWindow",
    "acceptsArbitraryProps": true,
    "props": []
  },
  {
    "componentName": "ArrowRight",
    "filePath": "C:\\xampp\\htdocs\\projects\\python\\caspian-web\\src\\lib\\ppicons\\ArrowRight.py",
    "relativePath": "src/lib/ppicons/ArrowRight.py",
    "importRoute": "src.lib.ppicons.ArrowRight",
    "acceptsArbitraryProps": true,
    "props": []
  },
  {
    "componentName": "ArrowUpRight",
    "filePath": "C:\\xampp\\htdocs\\projects\\python\\caspian-web\\src\\lib\\ppicons\\ArrowUpRight.py",
    "relativePath": "src/lib/ppicons/ArrowUpRight.py",
    "importRoute": "src.lib.ppicons.ArrowUpRight",
    "acceptsArbitraryProps": true,
    "props": []
  },
  {
    "componentName": "BookOpen",
    "filePath": "C:\\xampp\\htdocs\\projects\\python\\caspian-web\\src\\lib\\ppicons\\BookOpen.py",
    "relativePath": "src/lib/ppicons/BookOpen.py",
    "importRoute": "src.lib.ppicons.BookOpen",
    "acceptsArbitraryProps": true,
    "props": []
  },
  {
    "componentName": "Box",
    "filePath": "C:\\xampp\\htdocs\\projects\\python\\caspian-web\\src\\lib\\ppicons\\Box.py",
    "relativePath": "src/lib/ppicons/Box.py",
    "importRoute": "src.lib.ppicons.Box",
    "acceptsArbitraryProps": true,
    "props": []
  },
  {
    "componentName": "Braces",
    "filePath": "C:\\xampp\\htdocs\\projects\\python\\caspian-web\\src\\lib\\ppicons\\Braces.py",
    "relativePath": "src/lib/ppicons/Braces.py",
    "importRoute": "src.lib.ppicons.Braces",
    "acceptsArbitraryProps": true,
    "props": []
  },
  {
    "componentName": "Check",
    "filePath": "C:\\xampp\\htdocs\\projects\\python\\caspian-web\\src\\lib\\ppicons\\Check.py",
    "relativePath": "src/lib/ppicons/Check.py",
    "importRoute": "src.lib.ppicons.Check",
    "acceptsArbitraryProps": true,
    "props": []
  },
  {
    "componentName": "ChevronRight",
    "filePath": "C:\\xampp\\htdocs\\projects\\python\\caspian-web\\src\\lib\\ppicons\\ChevronRight.py",
    "relativePath": "src/lib/ppicons/ChevronRight.py",
    "importRoute": "src.lib.ppicons.ChevronRight",
    "acceptsArbitraryProps": true,
    "props": []
  },
  {
    "componentName": "ChevronsRight",
    "filePath": "C:\\xampp\\htdocs\\projects\\python\\caspian-web\\src\\lib\\ppicons\\ChevronsRight.py",
    "relativePath": "src/lib/ppicons/ChevronsRight.py",
    "importRoute": "src.lib.ppicons.ChevronsRight",
    "acceptsArbitraryProps": true,
    "props": []
  },
  {
    "componentName": "CircleAlert",
    "filePath": "C:\\xampp\\htdocs\\projects\\python\\caspian-web\\src\\lib\\ppicons\\CircleAlert.py",
    "relativePath": "src/lib/ppicons/CircleAlert.py",
    "importRoute": "src.lib.ppicons.CircleAlert",
    "acceptsArbitraryProps": true,
    "props": []
  },
  {
    "componentName": "CircleCheck",
    "filePath": "C:\\xampp\\htdocs\\projects\\python\\caspian-web\\src\\lib\\ppicons\\CircleCheck.py",
    "relativePath": "src/lib/ppicons/CircleCheck.py",
    "importRoute": "src.lib.ppicons.CircleCheck",
    "acceptsArbitraryProps": true,
    "props": []
  },
  {
    "componentName": "Clock",
    "filePath": "C:\\xampp\\htdocs\\projects\\python\\caspian-web\\src\\lib\\ppicons\\Clock.py",
    "relativePath": "src/lib/ppicons/Clock.py",
    "importRoute": "src.lib.ppicons.Clock",
    "acceptsArbitraryProps": true,
    "props": []
  },
  {
    "componentName": "Code",
    "filePath": "C:\\xampp\\htdocs\\projects\\python\\caspian-web\\src\\lib\\ppicons\\Code.py",
    "relativePath": "src/lib/ppicons/Code.py",
    "importRoute": "src.lib.ppicons.Code",
    "acceptsArbitraryProps": true,
    "props": []
  },
  {
    "componentName": "Copy",
    "filePath": "C:\\xampp\\htdocs\\projects\\python\\caspian-web\\src\\lib\\ppicons\\Copy.py",
    "relativePath": "src/lib/ppicons/Copy.py",
    "importRoute": "src.lib.ppicons.Copy",
    "acceptsArbitraryProps": true,
    "props": []
  },
  {
    "componentName": "Cpu",
    "filePath": "C:\\xampp\\htdocs\\projects\\python\\caspian-web\\src\\lib\\ppicons\\Cpu.py",
    "relativePath": "src/lib/ppicons/Cpu.py",
    "importRoute": "src.lib.ppicons.Cpu",
    "acceptsArbitraryProps": true,
    "props": []
  },
  {
    "componentName": "Database",
    "filePath": "C:\\xampp\\htdocs\\projects\\python\\caspian-web\\src\\lib\\ppicons\\Database.py",
    "relativePath": "src/lib/ppicons/Database.py",
    "importRoute": "src.lib.ppicons.Database",
    "acceptsArbitraryProps": true,
    "props": []
  },
  {
    "componentName": "Download",
    "filePath": "C:\\xampp\\htdocs\\projects\\python\\caspian-web\\src\\lib\\ppicons\\Download.py",
    "relativePath": "src/lib/ppicons/Download.py",
    "importRoute": "src.lib.ppicons.Download",
    "acceptsArbitraryProps": true,
    "props": []
  },
  {
    "componentName": "ExternalLink",
    "filePath": "C:\\xampp\\htdocs\\projects\\python\\caspian-web\\src\\lib\\ppicons\\ExternalLink.py",
    "relativePath": "src/lib/ppicons/ExternalLink.py",
    "importRoute": "src.lib.ppicons.ExternalLink",
    "acceptsArbitraryProps": true,
    "props": []
  },
  {
    "componentName": "File",
    "filePath": "C:\\xampp\\htdocs\\projects\\python\\caspian-web\\src\\lib\\ppicons\\File.py",
    "relativePath": "src/lib/ppicons/File.py",
    "importRoute": "src.lib.ppicons.File",
    "acceptsArbitraryProps": true,
    "props": []
  },
  {
    "componentName": "FileCode",
    "filePath": "C:\\xampp\\htdocs\\projects\\python\\caspian-web\\src\\lib\\ppicons\\FileCode.py",
    "relativePath": "src/lib/ppicons/FileCode.py",
    "importRoute": "src.lib.ppicons.FileCode",
    "acceptsArbitraryProps": true,
    "props": []
  },
  {
    "componentName": "FileJson",
    "filePath": "C:\\xampp\\htdocs\\projects\\python\\caspian-web\\src\\lib\\ppicons\\FileJson.py",
    "relativePath": "src/lib/ppicons/FileJson.py",
    "importRoute": "src.lib.ppicons.FileJson",
    "acceptsArbitraryProps": true,
    "props": []
  },
  {
    "componentName": "FileQuestion",
    "filePath": "C:\\xampp\\htdocs\\projects\\python\\caspian-web\\src\\lib\\ppicons\\FileQuestion.py",
    "relativePath": "src/lib/ppicons/FileQuestion.py",
    "importRoute": "src.lib.ppicons.FileQuestion",
    "acceptsArbitraryProps": true,
    "props": []
  },
  {
    "componentName": "FileText",
    "filePath": "C:\\xampp\\htdocs\\projects\\python\\caspian-web\\src\\lib\\ppicons\\FileText.py",
    "relativePath": "src/lib/ppicons/FileText.py",
    "importRoute": "src.lib.ppicons.FileText",
    "acceptsArbitraryProps": true,
    "props": []
  },
  {
    "componentName": "FileWarning",
    "filePath": "C:\\xampp\\htdocs\\projects\\python\\caspian-web\\src\\lib\\ppicons\\FileWarning.py",
    "relativePath": "src/lib/ppicons/FileWarning.py",
    "importRoute": "src.lib.ppicons.FileWarning",
    "acceptsArbitraryProps": true,
    "props": []
  },
  {
    "componentName": "Fingerprint",
    "filePath": "C:\\xampp\\htdocs\\projects\\python\\caspian-web\\src\\lib\\ppicons\\Fingerprint.py",
    "relativePath": "src/lib/ppicons/Fingerprint.py",
    "importRoute": "src.lib.ppicons.Fingerprint",
    "acceptsArbitraryProps": true,
    "props": []
  },
  {
    "componentName": "Folder",
    "filePath": "C:\\xampp\\htdocs\\projects\\python\\caspian-web\\src\\lib\\ppicons\\Folder.py",
    "relativePath": "src/lib/ppicons/Folder.py",
    "importRoute": "src.lib.ppicons.Folder",
    "acceptsArbitraryProps": true,
    "props": []
  },
  {
    "componentName": "FolderTree",
    "filePath": "C:\\xampp\\htdocs\\projects\\python\\caspian-web\\src\\lib\\ppicons\\FolderTree.py",
    "relativePath": "src/lib/ppicons/FolderTree.py",
    "importRoute": "src.lib.ppicons.FolderTree",
    "acceptsArbitraryProps": true,
    "props": []
  },
  {
    "componentName": "Funel",
    "filePath": "C:\\xampp\\htdocs\\projects\\python\\caspian-web\\src\\lib\\ppicons\\Funel.py",
    "relativePath": "src/lib/ppicons/Funel.py",
    "importRoute": "src.lib.ppicons.Funel",
    "acceptsArbitraryProps": true,
    "props": []
  },
  {
    "componentName": "Ghost",
    "filePath": "C:\\xampp\\htdocs\\projects\\python\\caspian-web\\src\\lib\\ppicons\\Ghost.py",
    "relativePath": "src/lib/ppicons/Ghost.py",
    "importRoute": "src.lib.ppicons.Ghost",
    "acceptsArbitraryProps": true,
    "props": []
  },
  {
    "componentName": "GitFork",
    "filePath": "C:\\xampp\\htdocs\\projects\\python\\caspian-web\\src\\lib\\ppicons\\GitFork.py",
    "relativePath": "src/lib/ppicons/GitFork.py",
    "importRoute": "src.lib.ppicons.GitFork",
    "acceptsArbitraryProps": true,
    "props": []
  },
  {
    "componentName": "Github",
    "filePath": "C:\\xampp\\htdocs\\projects\\python\\caspian-web\\src\\lib\\ppicons\\Github.py",
    "relativePath": "src/lib/ppicons/Github.py",
    "importRoute": "src.lib.ppicons.Github",
    "acceptsArbitraryProps": true,
    "props": []
  },
  {
    "componentName": "Globe",
    "filePath": "C:\\xampp\\htdocs\\projects\\python\\caspian-web\\src\\lib\\ppicons\\Globe.py",
    "relativePath": "src/lib/ppicons/Globe.py",
    "importRoute": "src.lib.ppicons.Globe",
    "acceptsArbitraryProps": true,
    "props": []
  },
  {
    "componentName": "Keyboard",
    "filePath": "C:\\xampp\\htdocs\\projects\\python\\caspian-web\\src\\lib\\ppicons\\Keyboard.py",
    "relativePath": "src/lib/ppicons/Keyboard.py",
    "importRoute": "src.lib.ppicons.Keyboard",
    "acceptsArbitraryProps": true,
    "props": []
  },
  {
    "componentName": "Layers",
    "filePath": "C:\\xampp\\htdocs\\projects\\python\\caspian-web\\src\\lib\\ppicons\\Layers.py",
    "relativePath": "src/lib/ppicons/Layers.py",
    "importRoute": "src.lib.ppicons.Layers",
    "acceptsArbitraryProps": true,
    "props": []
  },
  {
    "componentName": "LayoutDashboard",
    "filePath": "C:\\xampp\\htdocs\\projects\\python\\caspian-web\\src\\lib\\ppicons\\LayoutDashboard.py",
    "relativePath": "src/lib/ppicons/LayoutDashboard.py",
    "importRoute": "src.lib.ppicons.LayoutDashboard",
    "acceptsArbitraryProps": true,
    "props": []
  },
  {
    "componentName": "LayoutTemplate",
    "filePath": "C:\\xampp\\htdocs\\projects\\python\\caspian-web\\src\\lib\\ppicons\\LayoutTemplate.py",
    "relativePath": "src/lib/ppicons/LayoutTemplate.py",
    "importRoute": "src.lib.ppicons.LayoutTemplate",
    "acceptsArbitraryProps": true,
    "props": []
  },
  {
    "componentName": "Lock",
    "filePath": "C:\\xampp\\htdocs\\projects\\python\\caspian-web\\src\\lib\\ppicons\\Lock.py",
    "relativePath": "src/lib/ppicons/Lock.py",
    "importRoute": "src.lib.ppicons.Lock",
    "acceptsArbitraryProps": true,
    "props": []
  },
  {
    "componentName": "Map",
    "filePath": "C:\\xampp\\htdocs\\projects\\python\\caspian-web\\src\\lib\\ppicons\\Map.py",
    "relativePath": "src/lib/ppicons/Map.py",
    "importRoute": "src.lib.ppicons.Map",
    "acceptsArbitraryProps": true,
    "props": []
  },
  {
    "componentName": "MapPinOff",
    "filePath": "C:\\xampp\\htdocs\\projects\\python\\caspian-web\\src\\lib\\ppicons\\MapPinOff.py",
    "relativePath": "src/lib/ppicons/MapPinOff.py",
    "importRoute": "src.lib.ppicons.MapPinOff",
    "acceptsArbitraryProps": true,
    "props": []
  },
  {
    "componentName": "Menu",
    "filePath": "C:\\xampp\\htdocs\\projects\\python\\caspian-web\\src\\lib\\ppicons\\Menu.py",
    "relativePath": "src/lib/ppicons/Menu.py",
    "importRoute": "src.lib.ppicons.Menu",
    "acceptsArbitraryProps": true,
    "props": []
  },
  {
    "componentName": "MessageSquare",
    "filePath": "C:\\xampp\\htdocs\\projects\\python\\caspian-web\\src\\lib\\ppicons\\MessageSquare.py",
    "relativePath": "src/lib/ppicons/MessageSquare.py",
    "importRoute": "src.lib.ppicons.MessageSquare",
    "acceptsArbitraryProps": true,
    "props": []
  },
  {
    "componentName": "Monitor",
    "filePath": "C:\\xampp\\htdocs\\projects\\python\\caspian-web\\src\\lib\\ppicons\\Monitor.py",
    "relativePath": "src/lib/ppicons/Monitor.py",
    "importRoute": "src.lib.ppicons.Monitor",
    "acceptsArbitraryProps": true,
    "props": []
  },
  {
    "componentName": "Moon",
    "filePath": "C:\\xampp\\htdocs\\projects\\python\\caspian-web\\src\\lib\\ppicons\\Moon.py",
    "relativePath": "src/lib/ppicons/Moon.py",
    "importRoute": "src.lib.ppicons.Moon",
    "acceptsArbitraryProps": true,
    "props": []
  },
  {
    "componentName": "PanelTop",
    "filePath": "C:\\xampp\\htdocs\\projects\\python\\caspian-web\\src\\lib\\ppicons\\PanelTop.py",
    "relativePath": "src/lib/ppicons/PanelTop.py",
    "importRoute": "src.lib.ppicons.PanelTop",
    "acceptsArbitraryProps": true,
    "props": []
  },
  {
    "componentName": "Play",
    "filePath": "C:\\xampp\\htdocs\\projects\\python\\caspian-web\\src\\lib\\ppicons\\Play.py",
    "relativePath": "src/lib/ppicons/Play.py",
    "importRoute": "src.lib.ppicons.Play",
    "acceptsArbitraryProps": true,
    "props": []
  },
  {
    "componentName": "Puzzle",
    "filePath": "C:\\xampp\\htdocs\\projects\\python\\caspian-web\\src\\lib\\ppicons\\Puzzle.py",
    "relativePath": "src/lib/ppicons/Puzzle.py",
    "importRoute": "src.lib.ppicons.Puzzle",
    "acceptsArbitraryProps": true,
    "props": []
  },
  {
    "componentName": "RefreshCw",
    "filePath": "C:\\xampp\\htdocs\\projects\\python\\caspian-web\\src\\lib\\ppicons\\RefreshCw.py",
    "relativePath": "src/lib/ppicons/RefreshCw.py",
    "importRoute": "src.lib.ppicons.RefreshCw",
    "acceptsArbitraryProps": true,
    "props": []
  },
  {
    "componentName": "Rocket",
    "filePath": "C:\\xampp\\htdocs\\projects\\python\\caspian-web\\src\\lib\\ppicons\\Rocket.py",
    "relativePath": "src/lib/ppicons/Rocket.py",
    "importRoute": "src.lib.ppicons.Rocket",
    "acceptsArbitraryProps": true,
    "props": []
  },
  {
    "componentName": "Search",
    "filePath": "C:\\xampp\\htdocs\\projects\\python\\caspian-web\\src\\lib\\ppicons\\Search.py",
    "relativePath": "src/lib/ppicons/Search.py",
    "importRoute": "src.lib.ppicons.Search",
    "acceptsArbitraryProps": true,
    "props": []
  },
  {
    "componentName": "SearchX",
    "filePath": "C:\\xampp\\htdocs\\projects\\python\\caspian-web\\src\\lib\\ppicons\\SearchX.py",
    "relativePath": "src/lib/ppicons/SearchX.py",
    "importRoute": "src.lib.ppicons.SearchX",
    "acceptsArbitraryProps": true,
    "props": []
  },
  {
    "componentName": "Server",
    "filePath": "C:\\xampp\\htdocs\\projects\\python\\caspian-web\\src\\lib\\ppicons\\Server.py",
    "relativePath": "src/lib/ppicons/Server.py",
    "importRoute": "src.lib.ppicons.Server",
    "acceptsArbitraryProps": true,
    "props": []
  },
  {
    "componentName": "Settings",
    "filePath": "C:\\xampp\\htdocs\\projects\\python\\caspian-web\\src\\lib\\ppicons\\Settings.py",
    "relativePath": "src/lib/ppicons/Settings.py",
    "importRoute": "src.lib.ppicons.Settings",
    "acceptsArbitraryProps": true,
    "props": []
  },
  {
    "componentName": "Shield",
    "filePath": "C:\\xampp\\htdocs\\projects\\python\\caspian-web\\src\\lib\\ppicons\\Shield.py",
    "relativePath": "src/lib/ppicons/Shield.py",
    "importRoute": "src.lib.ppicons.Shield",
    "acceptsArbitraryProps": true,
    "props": []
  },
  {
    "componentName": "ShieldAlert",
    "filePath": "C:\\xampp\\htdocs\\projects\\python\\caspian-web\\src\\lib\\ppicons\\ShieldAlert.py",
    "relativePath": "src/lib/ppicons/ShieldAlert.py",
    "importRoute": "src.lib.ppicons.ShieldAlert",
    "acceptsArbitraryProps": true,
    "props": []
  },
  {
    "componentName": "Sparkles",
    "filePath": "C:\\xampp\\htdocs\\projects\\python\\caspian-web\\src\\lib\\ppicons\\Sparkles.py",
    "relativePath": "src/lib/ppicons/Sparkles.py",
    "importRoute": "src.lib.ppicons.Sparkles",
    "acceptsArbitraryProps": true,
    "props": []
  },
  {
    "componentName": "Sun",
    "filePath": "C:\\xampp\\htdocs\\projects\\python\\caspian-web\\src\\lib\\ppicons\\Sun.py",
    "relativePath": "src/lib/ppicons/Sun.py",
    "importRoute": "src.lib.ppicons.Sun",
    "acceptsArbitraryProps": true,
    "props": []
  },
  {
    "componentName": "Table",
    "filePath": "C:\\xampp\\htdocs\\projects\\python\\caspian-web\\src\\lib\\ppicons\\Table.py",
    "relativePath": "src/lib/ppicons/Table.py",
    "importRoute": "src.lib.ppicons.Table",
    "acceptsArbitraryProps": true,
    "props": []
  },
  {
    "componentName": "Terminal",
    "filePath": "C:\\xampp\\htdocs\\projects\\python\\caspian-web\\src\\lib\\ppicons\\Terminal.py",
    "relativePath": "src/lib/ppicons/Terminal.py",
    "importRoute": "src.lib.ppicons.Terminal",
    "acceptsArbitraryProps": true,
    "props": []
  },
  {
    "componentName": "TriangleAlert",
    "filePath": "C:\\xampp\\htdocs\\projects\\python\\caspian-web\\src\\lib\\ppicons\\TriangleAlert.py",
    "relativePath": "src/lib/ppicons/TriangleAlert.py",
    "importRoute": "src.lib.ppicons.TriangleAlert",
    "acceptsArbitraryProps": true,
    "props": []
  },
  {
    "componentName": "Twitter",
    "filePath": "C:\\xampp\\htdocs\\projects\\python\\caspian-web\\src\\lib\\ppicons\\Twitter.py",
    "relativePath": "src/lib/ppicons/Twitter.py",
    "importRoute": "src.lib.ppicons.Twitter",
    "acceptsArbitraryProps": true,
    "props": []
  },
  {
    "componentName": "Type",
    "filePath": "C:\\xampp\\htdocs\\projects\\python\\caspian-web\\src\\lib\\ppicons\\Type.py",
    "relativePath": "src/lib/ppicons/Type.py",
    "importRoute": "src.lib.ppicons.Type",
    "acceptsArbitraryProps": true,
    "props": []
  },
  {
    "componentName": "User",
    "filePath": "C:\\xampp\\htdocs\\projects\\python\\caspian-web\\src\\lib\\ppicons\\User.py",
    "relativePath": "src/lib/ppicons/User.py",
    "importRoute": "src.lib.ppicons.User",
    "acceptsArbitraryProps": true,
    "props": []
  },
  {
    "componentName": "X",
    "filePath": "C:\\xampp\\htdocs\\projects\\python\\caspian-web\\src\\lib\\ppicons\\X.py",
    "relativePath": "src/lib/ppicons/X.py",
    "importRoute": "src.lib.ppicons.X",
    "acceptsArbitraryProps": true,
    "props": []
  },
  {
    "componentName": "Zap",
    "filePath": "C:\\xampp\\htdocs\\projects\\python\\caspian-web\\src\\lib\\ppicons\\Zap.py",
    "relativePath": "src/lib/ppicons/Zap.py",
    "importRoute": "src.lib.ppicons.Zap",
    "acceptsArbitraryProps": true,
    "props": []
  }
]